waterlily/__init__.py
waterlily-0.0.0.dist-info/METADATA
waterlily-0.0.0.dist-info/WHEEL
waterlily-0.0.0.dist-info/licenses/LICENSE
waterlily-0.0.0.dist-info/RECORD
