Metadata-Version: 2.3
Name: waterlily
Version: 0.0.0
Summary: waterlily
License-File: LICENSE
Requires-Python: >=3.10
